topsis_Shamma_102253003/__init__.py
topsis_Shamma_102253003/topsis.py
topsis_Shamma_102253003-1.0.0.dist-info/METADATA
topsis_Shamma_102253003-1.0.0.dist-info/WHEEL
topsis_Shamma_102253003-1.0.0.dist-info/entry_points.txt
topsis_Shamma_102253003-1.0.0.dist-info/top_level.txt
topsis_Shamma_102253003-1.0.0.dist-info/RECORD
