Metadata-Version: 2.2
Name: topsis_Shamma_102253003
Version: 1.0.0
Summary: A Python package to perform TOPSIS.
Home-page: https://github.com/Shamma18/topsis
Author: Shamma
Author-email: sshamma_be22@thapar.edu
Classifier: Programming Language :: Python :: 3
Classifier: License :: OSI Approved :: MIT License
Classifier: Operating System :: OS Independent
Requires-Python: >=3.6
Requires-Dist: numpy
Requires-Dist: pandas
Dynamic: author
Dynamic: author-email
Dynamic: classifier
Dynamic: description
Dynamic: description-content-type
Dynamic: home-page
Dynamic: requires-dist
Dynamic: requires-python
Dynamic: summary
